.DS_Store
GraphHierarchy/GraphHierarchy.py
GraphHierarchy/__init__.py
GraphHierarchy-1.8.dist-info/LICENSE
GraphHierarchy-1.8.dist-info/METADATA
GraphHierarchy-1.8.dist-info/WHEEL
GraphHierarchy-1.8.dist-info/top_level.txt
GraphHierarchy-1.8.dist-info/RECORD
