Metadata-Version: 2.1
Name: GraphHierarchy
Version: 1.8
Summary: A module calculating quantities related to a network metric known as trophic coherence but now generalised to all networks, see Moutsinas, G., Shuaib, C., Guo, W., & Jarvis, S. (2019). Graph hierarchy and spread of infections. arXiv preprint arXiv:1908.04358 for more details.
Home-page: https://github.com/shuaib7860/GraphHierarchy
Author: Choudhry Shuaib
Author-email: cshuaib@outlook.com
License: MIT
Download-URL: https://github.com/shuaib7860/GraphHierarchy/archive/v1.8.tar.gz
Keywords: Graph Hierarchy,Trophic Coherence,Hierarchical Coherence,Trophic Levels,Hierarchical Levels,Influence Centrality,Democracy Coefficient
Platform: UNKNOWN
Classifier: Development Status :: 5 - Production/Stable
Classifier: Intended Audience :: Science/Research
Classifier: Topic :: Scientific/Engineering :: Physics
Classifier: Topic :: Scientific/Engineering :: Mathematics
Classifier: Topic :: Scientific/Engineering :: Information Analysis
Classifier: License :: OSI Approved :: MIT License
Classifier: Programming Language :: Python :: 3.5
Classifier: Programming Language :: Python :: 3.6
Classifier: Programming Language :: Python :: 3.7
Classifier: Programming Language :: Python :: 3.8
Requires-Dist: numpy
Requires-Dist: scipy
Requires-Dist: networkx
